statscanpy/StatsCanPy.py
statscanpy/__init__.py
statscanpy-1.1.1.dist-info/METADATA
statscanpy-1.1.1.dist-info/WHEEL
statscanpy-1.1.1.dist-info/top_level.txt
statscanpy-1.1.1.dist-info/RECORD
