Metadata-Version: 2.1
Name: statscanpy
Version: 1.1.1
Summary: Basic package for querying & downloading StatsCan data by table name.
Requires-Dist: pyspark
Requires-Dist: pandas
